researchplot/__init__.py
researchplot/config.py
researchplot/plots.py
researchplot-0.1.0.dist-info/METADATA
researchplot-0.1.0.dist-info/WHEEL
researchplot-0.1.0.dist-info/top_level.txt
researchplot-0.1.0.dist-info/RECORD
